odoo/addons/web_widget_google_map_drawing/README.rst
odoo/addons/web_widget_google_map_drawing/__init__.py
odoo/addons/web_widget_google_map_drawing/__manifest__.py
odoo/addons/web_widget_google_map_drawing/data/google_maps_library.xml
odoo/addons/web_widget_google_map_drawing/i18n/web_widget_google_map_drawing.pot
odoo/addons/web_widget_google_map_drawing/models/__init__.py
odoo/addons/web_widget_google_map_drawing/models/drawing_mixin.py
odoo/addons/web_widget_google_map_drawing/models/res_config_settings.py
odoo/addons/web_widget_google_map_drawing/readme/CONTRIBUTORS.rst
odoo/addons/web_widget_google_map_drawing/readme/DESCRIPTION.rst
odoo/addons/web_widget_google_map_drawing/readme/USAGE.rst
odoo/addons/web_widget_google_map_drawing/security/ir.model.access.csv
odoo/addons/web_widget_google_map_drawing/static/description/icon.png
odoo/addons/web_widget_google_map_drawing/static/description/index.html
odoo/addons/web_widget_google_map_drawing/static/description/thumbnails.png
odoo/addons/web_widget_google_map_drawing/static/src/js/widget/field_gmaps_drawing.js
odoo/addons/web_widget_google_map_drawing/static/src/js/widget/fields_registry.js
odoo/addons/web_widget_google_map_drawing/static/src/xml/drawing.xml
odoo/addons/web_widget_google_map_drawing/views/res_config_settings_views.xml
odoo/addons/web_widget_google_map_drawing/views/template.xml
odoo12_addon_web_widget_google_map_drawing-12.0.1.1.0.dist-info/METADATA
odoo12_addon_web_widget_google_map_drawing-12.0.1.1.0.dist-info/WHEEL
odoo12_addon_web_widget_google_map_drawing-12.0.1.1.0.dist-info/top_level.txt
odoo12_addon_web_widget_google_map_drawing-12.0.1.1.0.dist-info/RECORD
