Metadata-Version: 2.1
Name: odoo12-addon-web-widget-google-map-drawing
Version: 12.0.1.1.0
Summary: Add drawing tools to Google Map view in Odoo
Home-page: https://github.com/OCA/geospatial
Author: Yopi Angi, Odoo Community Association (OCA)
Author-email: support@odoo-community.org
License: AGPL-3
Platform: UNKNOWN
Classifier: Programming Language :: Python
Classifier: Framework :: Odoo
Classifier: Framework :: Odoo :: 12.0
Classifier: License :: OSI Approved :: GNU Affero General Public License v3
Requires-Python: >=3.5
Requires-Dist: odoo12-addon-web-view-google-map
Requires-Dist: odoo <12.1dev,>=12.0a
